[
  {
    "euro": 40.98,
    "timestamp": 1612051200
  },
  {
    "euro": 40.509998,
    "timestamp": 1612054800
  },
  {
    "euro": 39.5,
    "timestamp": 1612058400
  },
  {
    "euro": 39.549999,
    "timestamp": 1612062000
  },
  {
    "euro": 40.41,
    "timestamp": 1612065600
  },
  {
    "euro": 40.419998,
    "timestamp": 1612069200
  },
  {
    "euro": 41.290001,
    "timestamp": 1612072800
  },
  {
    "euro": 44.849998,
    "timestamp": 1612076400
  },
  {
    "euro": 49.150002,
    "timestamp": 1612080000
  },
  {
    "euro": 50.73,
    "timestamp": 1612083600
  },
  {
    "euro": 51.139999,
    "timestamp": 1612087200
  },
  {
    "euro": 50.369999,
    "timestamp": 1612090800
  },
  {
    "euro": 46.23,
    "timestamp": 1612094400
  },
  {
    "euro": 45.900002,
    "timestamp": 1612098000
  },
  {
    "euro": 47.919998,
    "timestamp": 1612101600
  },
  {
    "euro": 52.919998,
    "timestamp": 1612105200
  },
  {
    "euro": 64.459999,
    "timestamp": 1612108800
  },
  {
    "euro": 63.880001,
    "timestamp": 1612112400
  },
  {
    "euro": 62.349998,
    "timestamp": 1612116000
  },
  {
    "euro": 57.990002,
    "timestamp": 1612119600
  },
  {
    "euro": 51.34,
    "timestamp": 1612123200
  },
  {
    "euro": 49.279999,
    "timestamp": 1612126800
  },
  {
    "euro": 45.360001,
    "timestamp": 1612130400
  },
  {
    "euro": 42.549999,
    "timestamp": 1612134000
  }
]
