[
  {
    "timestamp": 1735344000,
    "sources": [
      {
        "type": "offshore wind",
        "energy": 259.83
      },
      {
        "type": "onshore wind",
        "energy": 244.71
      },
      {
        "type": "solar",
        "energy": 0
      }
    ]
  },
  {
    "timestamp": 1735347600,
    "sources": [
      {
        "type": "offshore wind",
        "energy": 270.42
      },
      {
        "type": "onshore wind",
        "energy": 262.04
      },
      {
        "type": "solar",
        "energy": 0
      }
    ]
  },
  {
    "timestamp": 1735351200,
    "sources": [
      {
        "type": "offshore wind",
        "energy": 277.04
      },
      {
        "type": "onshore wind",
        "energy": 285.92
      },
      {
        "type": "solar",
        "energy": 0
      }
    ]
  },
  {
    "timestamp": 1735354800,
    "sources": [
      {
        "type": "offshore wind",
        "energy": 271.13
      },
      {
        "type": "onshore wind",
        "energy": 301.96
      },
      {
        "type": "solar",
        "energy": 0
      }
    ]
  },
  {
    "timestamp": 1735358400,
    "sources": [
      {
        "type": "offshore wind",
        "energy": 260.17
      },
      {
        "type": "onshore wind",
        "energy": 318.29
      },
      {
        "type": "solar",
        "energy": 0
      }
    ]
  },
  {
    "timestamp": 1735362000,
    "sources": [
      {
        "type": "offshore wind",
        "energy": 263.58
      },
      {
        "type": "onshore wind",
        "energy": 304.63
      },
      {
        "type": "solar",
        "energy": 0
      }
    ]
  },
  {
    "timestamp": 1735365600,
    "sources": [
      {
        "type": "offshore wind",
        "energy": 282.79
      },
      {
        "type": "onshore wind",
        "energy": 315.79
      },
      {
        "type": "solar",
        "energy": 0
      }
    ]
  },
  {
    "timestamp": 1735369200,
    "sources": [
      {
        "type": "offshore wind",
        "energy": 319.04
      },
      {
        "type": "onshore wind",
        "energy": 362
      },
      {
        "type": "solar",
        "energy": 0.36
      }
    ]
  },
  {
    "timestamp": 1735372800,
    "sources": [
      {
        "type": "offshore wind",
        "energy": 350.67
      },
      {
        "type": "onshore wind",
        "energy": 397
      },
      {
        "type": "solar",
        "energy": 10.79
      }
    ]
  },
  {
    "timestamp": 1735376400,
    "sources": [
      {
        "type": "offshore wind",
        "energy": 376
      },
      {
        "type": "onshore wind",
        "energy": 433.63
      },
      {
        "type": "solar",
        "energy": 73.53
      }
    ]
  },
  {
    "timestamp": 1735380000,
    "sources": [
      {
        "type": "offshore wind",
        "energy": 385.08
      },
      {
        "type": "onshore wind",
        "energy": 458.75
      },
      {
        "type": "solar",
        "energy": 121.07
      }
    ]
  },
  {
    "timestamp": 1735383600,
    "sources": [
      {
        "type": "offshore wind",
        "energy": 386.08
      },
      {
        "type": "onshore wind",
        "energy": 474.13
      },
      {
        "type": "solar",
        "energy": 129.14
      }
    ]
  },
  {
    "timestamp": 1735387200,
    "sources": [
      {
        "type": "offshore wind",
        "energy": 399.83
      },
      {
        "type": "onshore wind",
        "energy": 481.88
      },
      {
        "type": "solar",
        "energy": 109.2
      }
    ]
  },
  {
    "timestamp": 1735390800,
    "sources": [
      {
        "type": "offshore wind",
        "energy": 428.88
      },
      {
        "type": "onshore wind",
        "energy": 506.04
      },
      {
        "type": "solar",
        "energy": 56.26
      }
    ]
  },
  {
    "timestamp": 1735394400,
    "sources": [
      {
        "type": "offshore wind",
        "energy": 460.58
      },
      {
        "type": "onshore wind",
        "energy": 538.38
      },
      {
        "type": "solar",
        "energy": 6.84
      }
    ]
  },
  {
    "timestamp": 1735398000,
    "sources": [
      {
        "type": "offshore wind",
        "energy": 468.79
      },
      {
        "type": "onshore wind",
        "energy": 583.92
      },
      {
        "type": "solar",
        "energy": 0.32
      }
    ]
  },
  {
    "timestamp": 1735401600,
    "sources": [
      {
        "type": "offshore wind",
        "energy": 485.79
      },
      {
        "type": "onshore wind",
        "energy": 590.58
      },
      {
        "type": "solar",
        "energy": 0
      }
    ]
  },
  {
    "timestamp": 1735405200,
    "sources": [
      {
        "type": "offshore wind",
        "energy": 504.04
      },
      {
        "type": "onshore wind",
        "energy": 590
      },
      {
        "type": "solar",
        "energy": 0
      }
    ]
  },
  {
    "timestamp": 1735408800,
    "sources": [
      {
        "type": "offshore wind",
        "energy": 515.71
      },
      {
        "type": "onshore wind",
        "energy": 660.17
      },
      {
        "type": "solar",
        "energy": 0
      }
    ]
  },
  {
    "timestamp": 1735412400,
    "sources": [
      {
        "type": "offshore wind",
        "energy": 531.17
      },
      {
        "type": "onshore wind",
        "energy": 742.58
      },
      {
        "type": "solar",
        "energy": 0
      }
    ]
  },
  {
    "timestamp": 1735416000,
    "sources": [
      {
        "type": "offshore wind",
        "energy": 537.38
      },
      {
        "type": "onshore wind",
        "energy": 801.88
      },
      {
        "type": "solar",
        "energy": 0
      }
    ]
  },
  {
    "timestamp": 1735419600,
    "sources": [
      {
        "type": "offshore wind",
        "energy": 556.67
      },
      {
        "type": "onshore wind",
        "energy": 846.88
      },
      {
        "type": "solar",
        "energy": 0
      }
    ]
  },
  {
    "timestamp": 1735423200,
    "sources": [
      {
        "type": "offshore wind",
        "energy": 582.33
      },
      {
        "type": "onshore wind",
        "energy": 875.92
      },
      {
        "type": "solar",
        "energy": 0
      }
    ]
  },
  {
    "timestamp": 1735426800,
    "sources": [
      {
        "type": "offshore wind",
        "energy": 569
      },
      {
        "type": "onshore wind",
        "energy": 1016.67
      },
      {
        "type": "solar",
        "energy": 0
      }
    ]
  }
]
