[
  {
    "co2": 76,
    "timestamp": 1632355200
  },
  {
    "co2": 77,
    "timestamp": 1632355500
  },
  {
    "co2": 77,
    "timestamp": 1632355800
  },
  {
    "co2": 76,
    "timestamp": 1632356100
  },
  {
    "co2": 75,
    "timestamp": 1632356400
  },
  {
    "co2": 74,
    "timestamp": 1632356700
  },
  {
    "co2": 74,
    "timestamp": 1632357000
  },
  {
    "co2": 74,
    "timestamp": 1632357300
  },
  {
    "co2": 73,
    "timestamp": 1632357600
  },
  {
    "co2": 74,
    "timestamp": 1632357900
  },
  {
    "co2": 77,
    "timestamp": 1632358200
  },
  {
    "co2": 78,
    "timestamp": 1632358500
  },
  {
    "co2": 80,
    "timestamp": 1632358800
  },
  {
    "co2": 82,
    "timestamp": 1632359100
  },
  {
    "co2": 81,
    "timestamp": 1632359400
  },
  {
    "co2": 76,
    "timestamp": 1632359700
  },
  {
    "co2": 79,
    "timestamp": 1632360000
  },
  {
    "co2": 76,
    "timestamp": 1632360300
  },
  {
    "co2": 81,
    "timestamp": 1632360600
  },
  {
    "co2": 92,
    "timestamp": 1632360900
  },
  {
    "co2": 94,
    "timestamp": 1632361200
  },
  {
    "co2": 90,
    "timestamp": 1632361500
  },
  {
    "co2": 89,
    "timestamp": 1632361800
  },
  {
    "co2": 86,
    "timestamp": 1632362100
  },
  {
    "co2": 86,
    "timestamp": 1632362400
  },
  {
    "co2": 84,
    "timestamp": 1632362700
  },
  {
    "co2": 78,
    "timestamp": 1632363000
  },
  {
    "co2": 77,
    "timestamp": 1632363300
  },
  {
    "co2": 78,
    "timestamp": 1632363600
  },
  {
    "co2": 75,
    "timestamp": 1632363900
  },
  {
    "co2": 71,
    "timestamp": 1632364200
  },
  {
    "co2": 77,
    "timestamp": 1632364500
  },
  {
    "co2": 76,
    "timestamp": 1632364800
  },
  {
    "co2": 77,
    "timestamp": 1632365100
  },
  {
    "co2": 78,
    "timestamp": 1632365400
  },
  {
    "co2": 86,
    "timestamp": 1632365700
  },
  {
    "co2": 89,
    "timestamp": 1632366000
  },
  {
    "co2": 83,
    "timestamp": 1632366300
  },
  {
    "co2": 71,
    "timestamp": 1632366600
  },
  {
    "co2": 78,
    "timestamp": 1632366900
  },
  {
    "co2": 80,
    "timestamp": 1632367200
  },
  {
    "co2": 83,
    "timestamp": 1632367500
  },
  {
    "co2": 80,
    "timestamp": 1632367800
  },
  {
    "co2": 85,
    "timestamp": 1632368100
  },
  {
    "co2": 81,
    "timestamp": 1632368400
  },
  {
    "co2": 81,
    "timestamp": 1632368700
  },
  {
    "co2": 84,
    "timestamp": 1632369000
  },
  {
    "co2": 85,
    "timestamp": 1632369300
  },
  {
    "co2": 78,
    "timestamp": 1632369600
  },
  {
    "co2": 80,
    "timestamp": 1632369900
  },
  {
    "co2": 75,
    "timestamp": 1632370200
  },
  {
    "co2": 72,
    "timestamp": 1632370500
  },
  {
    "co2": 71,
    "timestamp": 1632370800
  },
  {
    "co2": 71,
    "timestamp": 1632371100
  },
  {
    "co2": 67,
    "timestamp": 1632371400
  },
  {
    "co2": 69,
    "timestamp": 1632371700
  },
  {
    "co2": 72,
    "timestamp": 1632372000
  },
  {
    "co2": 71,
    "timestamp": 1632372300
  },
  {
    "co2": 77,
    "timestamp": 1632372600
  },
  {
    "co2": 66,
    "timestamp": 1632372900
  },
  {
    "co2": 63,
    "timestamp": 1632373200
  },
  {
    "co2": 72,
    "timestamp": 1632373500
  },
  {
    "co2": 75,
    "timestamp": 1632373800
  },
  {
    "co2": 74,
    "timestamp": 1632374100
  },
  {
    "co2": 74,
    "timestamp": 1632374400
  },
  {
    "co2": 74,
    "timestamp": 1632374700
  },
  {
    "co2": 71,
    "timestamp": 1632375000
  },
  {
    "co2": 70,
    "timestamp": 1632375300
  },
  {
    "co2": 67,
    "timestamp": 1632375600
  },
  {
    "co2": 71,
    "timestamp": 1632375900
  },
  {
    "co2": 78,
    "timestamp": 1632376200
  },
  {
    "co2": 75,
    "timestamp": 1632376500
  },
  {
    "co2": 77,
    "timestamp": 1632376800
  },
  {
    "co2": 73,
    "timestamp": 1632377100
  },
  {
    "co2": 70,
    "timestamp": 1632377400
  },
  {
    "co2": 73,
    "timestamp": 1632377700
  },
  {
    "co2": 69,
    "timestamp": 1632378000
  },
  {
    "co2": 68,
    "timestamp": 1632378300
  },
  {
    "co2": 68,
    "timestamp": 1632378600
  },
  {
    "co2": 68,
    "timestamp": 1632378900
  },
  {
    "co2": 67,
    "timestamp": 1632379200
  },
  {
    "co2": 67,
    "timestamp": 1632379500
  },
  {
    "co2": 70,
    "timestamp": 1632379800
  },
  {
    "co2": 75,
    "timestamp": 1632380100
  },
  {
    "co2": 75,
    "timestamp": 1632380400
  },
  {
    "co2": 86,
    "timestamp": 1632380700
  },
  {
    "co2": 86,
    "timestamp": 1632381000
  },
  {
    "co2": 77,
    "timestamp": 1632381300
  },
  {
    "co2": 76,
    "timestamp": 1632381600
  },
  {
    "co2": 73,
    "timestamp": 1632381900
  },
  {
    "co2": 73,
    "timestamp": 1632382200
  },
  {
    "co2": 73,
    "timestamp": 1632382500
  },
  {
    "co2": 74,
    "timestamp": 1632382800
  },
  {
    "co2": 80,
    "timestamp": 1632383100
  },
  {
    "co2": 82,
    "timestamp": 1632383400
  },
  {
    "co2": 89,
    "timestamp": 1632383700
  },
  {
    "co2": 89,
    "timestamp": 1632384000
  },
  {
    "co2": 79,
    "timestamp": 1632384300
  },
  {
    "co2": 72,
    "timestamp": 1632384600
  },
  {
    "co2": 70,
    "timestamp": 1632384900
  },
  {
    "co2": 68,
    "timestamp": 1632385200
  },
  {
    "co2": 66,
    "timestamp": 1632385500
  },
  {
    "co2": 61,
    "timestamp": 1632385800
  },
  {
    "co2": 69,
    "timestamp": 1632386100
  },
  {
    "co2": 69,
    "timestamp": 1632386400
  },
  {
    "co2": 79,
    "timestamp": 1632386700
  },
  {
    "co2": 73,
    "timestamp": 1632387000
  },
  {
    "co2": 65,
    "timestamp": 1632387300
  },
  {
    "co2": 56,
    "timestamp": 1632387600
  },
  {
    "co2": 62,
    "timestamp": 1632387900
  },
  {
    "co2": 66,
    "timestamp": 1632388200
  },
  {
    "co2": 63,
    "timestamp": 1632388500
  },
  {
    "co2": 60,
    "timestamp": 1632388800
  },
  {
    "co2": 57,
    "timestamp": 1632389100
  },
  {
    "co2": 59,
    "timestamp": 1632389400
  },
  {
    "co2": 57,
    "timestamp": 1632389700
  },
  {
    "co2": 55,
    "timestamp": 1632390000
  },
  {
    "co2": 57,
    "timestamp": 1632390300
  },
  {
    "co2": 56,
    "timestamp": 1632390600
  },
  {
    "co2": 57,
    "timestamp": 1632390900
  },
  {
    "co2": 53,
    "timestamp": 1632391200
  },
  {
    "co2": 52,
    "timestamp": 1632391500
  },
  {
    "co2": 52,
    "timestamp": 1632391800
  },
  {
    "co2": 53,
    "timestamp": 1632392100
  },
  {
    "co2": 51,
    "timestamp": 1632392400
  },
  {
    "co2": 51,
    "timestamp": 1632392700
  },
  {
    "co2": 52,
    "timestamp": 1632393000
  },
  {
    "co2": 52,
    "timestamp": 1632393300
  },
  {
    "co2": 52,
    "timestamp": 1632393600
  },
  {
    "co2": 52,
    "timestamp": 1632393900
  },
  {
    "co2": 53,
    "timestamp": 1632394200
  },
  {
    "co2": 53,
    "timestamp": 1632394500
  },
  {
    "co2": 45,
    "timestamp": 1632394800
  },
  {
    "co2": 46,
    "timestamp": 1632395100
  },
  {
    "co2": 49,
    "timestamp": 1632395400
  },
  {
    "co2": 49,
    "timestamp": 1632395700
  },
  {
    "co2": 45,
    "timestamp": 1632396000
  },
  {
    "co2": 41,
    "timestamp": 1632396300
  },
  {
    "co2": 40,
    "timestamp": 1632396600
  },
  {
    "co2": 41,
    "timestamp": 1632396900
  },
  {
    "co2": 38,
    "timestamp": 1632397200
  },
  {
    "co2": 38,
    "timestamp": 1632397500
  },
  {
    "co2": 39,
    "timestamp": 1632397800
  },
  {
    "co2": 40,
    "timestamp": 1632398100
  },
  {
    "co2": 40,
    "timestamp": 1632398400
  },
  {
    "co2": 39,
    "timestamp": 1632398700
  },
  {
    "co2": 37,
    "timestamp": 1632399000
  },
  {
    "co2": 39,
    "timestamp": 1632399300
  },
  {
    "co2": 39,
    "timestamp": 1632399600
  },
  {
    "co2": 40,
    "timestamp": 1632399900
  },
  {
    "co2": 40,
    "timestamp": 1632400200
  },
  {
    "co2": 40,
    "timestamp": 1632400500
  },
  {
    "co2": 40,
    "timestamp": 1632400800
  },
  {
    "co2": 41,
    "timestamp": 1632401100
  },
  {
    "co2": 43,
    "timestamp": 1632401400
  },
  {
    "co2": 44,
    "timestamp": 1632401700
  },
  {
    "co2": 46,
    "timestamp": 1632402000
  },
  {
    "co2": 46,
    "timestamp": 1632402300
  },
  {
    "co2": 48,
    "timestamp": 1632402600
  },
  {
    "co2": 47,
    "timestamp": 1632402900
  },
  {
    "co2": 47,
    "timestamp": 1632403200
  },
  {
    "co2": 42,
    "timestamp": 1632403500
  },
  {
    "co2": 45,
    "timestamp": 1632403800
  },
  {
    "co2": 45,
    "timestamp": 1632404100
  },
  {
    "co2": 39,
    "timestamp": 1632404400
  },
  {
    "co2": 38,
    "timestamp": 1632404700
  },
  {
    "co2": 40,
    "timestamp": 1632405000
  },
  {
    "co2": 40,
    "timestamp": 1632405300
  },
  {
    "co2": 40,
    "timestamp": 1632405600
  },
  {
    "co2": 40,
    "timestamp": 1632405900
  },
  {
    "co2": 40,
    "timestamp": 1632406200
  },
  {
    "co2": 47,
    "timestamp": 1632406500
  },
  {
    "co2": 49,
    "timestamp": 1632406800
  },
  {
    "co2": 47,
    "timestamp": 1632407100
  },
  {
    "co2": 46,
    "timestamp": 1632407400
  },
  {
    "co2": 48,
    "timestamp": 1632407700
  },
  {
    "co2": 45,
    "timestamp": 1632408000
  },
  {
    "co2": 47,
    "timestamp": 1632408300
  },
  {
    "co2": 46,
    "timestamp": 1632408600
  },
  {
    "co2": 47,
    "timestamp": 1632408900
  },
  {
    "co2": 49,
    "timestamp": 1632409200
  },
  {
    "co2": 55,
    "timestamp": 1632409500
  },
  {
    "co2": 59,
    "timestamp": 1632409800
  },
  {
    "co2": 73,
    "timestamp": 1632410100
  },
  {
    "co2": 74,
    "timestamp": 1632410400
  },
  {
    "co2": 75,
    "timestamp": 1632410700
  },
  {
    "co2": 75,
    "timestamp": 1632411000
  },
  {
    "co2": 77,
    "timestamp": 1632411300
  },
  {
    "co2": 77,
    "timestamp": 1632411600
  },
  {
    "co2": 78,
    "timestamp": 1632411900
  },
  {
    "co2": 83,
    "timestamp": 1632412200
  },
  {
    "co2": 89,
    "timestamp": 1632412500
  },
  {
    "co2": 89,
    "timestamp": 1632412800
  },
  {
    "co2": 81,
    "timestamp": 1632413100
  },
  {
    "co2": 72,
    "timestamp": 1632413400
  },
  {
    "co2": 98,
    "timestamp": 1632413700
  },
  {
    "co2": 91,
    "timestamp": 1632414000
  },
  {
    "co2": 88,
    "timestamp": 1632414300
  },
  {
    "co2": 89,
    "timestamp": 1632414600
  },
  {
    "co2": 90,
    "timestamp": 1632414900
  },
  {
    "co2": 89,
    "timestamp": 1632415200
  },
  {
    "co2": 89,
    "timestamp": 1632415500
  },
  {
    "co2": 91,
    "timestamp": 1632415800
  },
  {
    "co2": 95,
    "timestamp": 1632416100
  },
  {
    "co2": 101,
    "timestamp": 1632416400
  },
  {
    "co2": 98,
    "timestamp": 1632416700
  },
  {
    "co2": 95,
    "timestamp": 1632417000
  },
  {
    "co2": 108,
    "timestamp": 1632417300
  },
  {
    "co2": 102,
    "timestamp": 1632417600
  },
  {
    "co2": 99,
    "timestamp": 1632417900
  },
  {
    "co2": 102,
    "timestamp": 1632418200
  },
  {
    "co2": 102,
    "timestamp": 1632418500
  },
  {
    "co2": 102,
    "timestamp": 1632418800
  },
  {
    "co2": 102,
    "timestamp": 1632419100
  },
  {
    "co2": 102,
    "timestamp": 1632419400
  },
  {
    "co2": 101,
    "timestamp": 1632419700
  },
  {
    "co2": 98,
    "timestamp": 1632420000
  },
  {
    "co2": 101,
    "timestamp": 1632420300
  },
  {
    "co2": 101,
    "timestamp": 1632420600
  },
  {
    "co2": 101,
    "timestamp": 1632420900
  },
  {
    "co2": 98,
    "timestamp": 1632421200
  },
  {
    "co2": 98,
    "timestamp": 1632421500
  },
  {
    "co2": 98,
    "timestamp": 1632421800
  },
  {
    "co2": 99,
    "timestamp": 1632422100
  },
  {
    "co2": 99,
    "timestamp": 1632422400
  },
  {
    "co2": 99,
    "timestamp": 1632422700
  },
  {
    "co2": 99,
    "timestamp": 1632423000
  },
  {
    "co2": 97,
    "timestamp": 1632423300
  },
  {
    "co2": 92,
    "timestamp": 1632423600
  },
  {
    "co2": 94,
    "timestamp": 1632423900
  },
  {
    "co2": 92,
    "timestamp": 1632424200
  },
  {
    "co2": 91,
    "timestamp": 1632424500
  },
  {
    "co2": 90,
    "timestamp": 1632424800
  },
  {
    "co2": 91,
    "timestamp": 1632425100
  },
  {
    "co2": 90,
    "timestamp": 1632425400
  },
  {
    "co2": 90,
    "timestamp": 1632425700
  },
  {
    "co2": 89,
    "timestamp": 1632426000
  },
  {
    "co2": 89,
    "timestamp": 1632426300
  },
  {
    "co2": 87,
    "timestamp": 1632426600
  },
  {
    "co2": 85,
    "timestamp": 1632426900
  },
  {
    "co2": 57,
    "timestamp": 1632427200
  },
  {
    "co2": 58,
    "timestamp": 1632427500
  },
  {
    "co2": 59,
    "timestamp": 1632427800
  },
  {
    "co2": 56,
    "timestamp": 1632428100
  },
  {
    "co2": 57,
    "timestamp": 1632428400
  },
  {
    "co2": 57,
    "timestamp": 1632428700
  },
  {
    "co2": 57,
    "timestamp": 1632429000
  },
  {
    "co2": 58,
    "timestamp": 1632429300
  },
  {
    "co2": 57,
    "timestamp": 1632429600
  },
  {
    "co2": 57,
    "timestamp": 1632429900
  },
  {
    "co2": 57,
    "timestamp": 1632430200
  },
  {
    "co2": 56,
    "timestamp": 1632430500
  },
  {
    "co2": 50,
    "timestamp": 1632430800
  },
  {
    "co2": 51,
    "timestamp": 1632431100
  },
  {
    "co2": 50,
    "timestamp": 1632431400
  },
  {
    "co2": 50,
    "timestamp": 1632431700
  },
  {
    "co2": 51,
    "timestamp": 1632432000
  },
  {
    "co2": 51,
    "timestamp": 1632432300
  },
  {
    "co2": 52,
    "timestamp": 1632432600
  },
  {
    "co2": 59,
    "timestamp": 1632432900
  },
  {
    "co2": 59,
    "timestamp": 1632433200
  },
  {
    "co2": 61,
    "timestamp": 1632433500
  },
  {
    "co2": 61,
    "timestamp": 1632433800
  },
  {
    "co2": 63,
    "timestamp": 1632434100
  },
  {
    "co2": 60,
    "timestamp": 1632434400
  },
  {
    "co2": 74,
    "timestamp": 1632434700
  },
  {
    "co2": 72,
    "timestamp": 1632435000
  },
  {
    "co2": 72,
    "timestamp": 1632435300
  },
  {
    "co2": 71,
    "timestamp": 1632435600
  },
  {
    "co2": 67,
    "timestamp": 1632435900
  },
  {
    "co2": 71,
    "timestamp": 1632436200
  },
  {
    "co2": 73,
    "timestamp": 1632436500
  },
  {
    "co2": 74,
    "timestamp": 1632436800
  },
  {
    "co2": 73,
    "timestamp": 1632437100
  },
  {
    "co2": 77,
    "timestamp": 1632437400
  },
  {
    "co2": 78,
    "timestamp": 1632437700
  },
  {
    "co2": 74,
    "timestamp": 1632438000
  },
  {
    "co2": 77,
    "timestamp": 1632438300
  },
  {
    "co2": 73,
    "timestamp": 1632438600
  },
  {
    "co2": 74,
    "timestamp": 1632438900
  },
  {
    "co2": 75,
    "timestamp": 1632439200
  },
  {
    "co2": 65,
    "timestamp": 1632439500
  },
  {
    "co2": 66,
    "timestamp": 1632439800
  },
  {
    "co2": 74,
    "timestamp": 1632440100
  },
  {
    "co2": 76,
    "timestamp": 1632440400
  },
  {
    "co2": 75,
    "timestamp": 1632440700
  },
  {
    "co2": 76,
    "timestamp": 1632441000
  },
  {
    "co2": 77,
    "timestamp": 1632441300
  }
]
