[
  {
    "euro": 6.74,
    "timestamp": 962064000
  },
  {
    "euro": 6.46,
    "timestamp": 962067600
  },
  {
    "euro": 6.41,
    "timestamp": 962071200
  },
  {
    "euro": 7.61,
    "timestamp": 962074800
  },
  {
    "euro": 8.07,
    "timestamp": 962078400
  },
  {
    "euro": 9.54,
    "timestamp": 962082000
  },
  {
    "euro": 10.25,
    "timestamp": 962085600
  },
  {
    "euro": 10.82,
    "timestamp": 962089200
  },
  {
    "euro": 10.8,
    "timestamp": 962092800
  },
  {
    "euro": 10.54,
    "timestamp": 962096400
  },
  {
    "euro": 10.16,
    "timestamp": 962100000
  },
  {
    "euro": 9.7,
    "timestamp": 962103600
  },
  {
    "euro": 9.78,
    "timestamp": 962107200
  },
  {
    "euro": 10.22,
    "timestamp": 962110800
  },
  {
    "euro": 9.97,
    "timestamp": 962114400
  },
  {
    "euro": 9.73,
    "timestamp": 962118000
  },
  {
    "euro": 9.46,
    "timestamp": 962121600
  },
  {
    "euro": 9.29,
    "timestamp": 962125200
  },
  {
    "euro": 9.13,
    "timestamp": 962128800
  },
  {
    "euro": 9.04,
    "timestamp": 962132400
  },
  {
    "euro": 9.11,
    "timestamp": 962136000
  },
  {
    "euro": 8.57,
    "timestamp": 962139600
  },
  {
    "euro": 9.51,
    "timestamp": 962143200
  },
  {
    "euro": 9.05,
    "timestamp": 962146800
  }
]
