[
  {
    "euro": 169.449997,
    "timestamp": 1649289600
  },
  {
    "euro": 166.679993,
    "timestamp": 1649293200
  },
  {
    "euro": 165.899994,
    "timestamp": 1649296800
  },
  {
    "euro": 166,
    "timestamp": 1649300400
  },
  {
    "euro": 169.509995,
    "timestamp": 1649304000
  },
  {
    "euro": 171.729996,
    "timestamp": 1649307600
  },
  {
    "euro": 172.199997,
    "timestamp": 1649311200
  },
  {
    "euro": 171.130005,
    "timestamp": 1649314800
  },
  {
    "euro": 171.130005,
    "timestamp": 1649318400
  },
  {
    "euro": 170.559998,
    "timestamp": 1649322000
  },
  {
    "euro": 169.130005,
    "timestamp": 1649325600
  },
  {
    "euro": 167.589996,
    "timestamp": 1649329200
  },
  {
    "euro": 168.279999,
    "timestamp": 1649332800
  },
  {
    "euro": 168.580002,
    "timestamp": 1649336400
  },
  {
    "euro": 168.699997,
    "timestamp": 1649340000
  },
  {
    "euro": 170.839996,
    "timestamp": 1649343600
  },
  {
    "euro": 171.919998,
    "timestamp": 1649347200
  },
  {
    "euro": 171.699997,
    "timestamp": 1649350800
  },
  {
    "euro": 172.649994,
    "timestamp": 1649354400
  },
  {
    "euro": 172.5,
    "timestamp": 1649358000
  },
  {
    "euro": 171.410004,
    "timestamp": 1649361600
  },
  {
    "euro": 171.240005,
    "timestamp": 1649365200
  },
  {
    "euro": 168.850006,
    "timestamp": 1649368800
  },
  {
    "euro": 167.820007,
    "timestamp": 1649372400
  }
]
