[
  {
    "euro": 36.41,
    "timestamp": 1380499200
  },
  {
    "euro": 36.119999,
    "timestamp": 1380502800
  },
  {
    "euro": 36.68,
    "timestamp": 1380506400
  },
  {
    "euro": 37.259998,
    "timestamp": 1380510000
  },
  {
    "euro": 37.259998,
    "timestamp": 1380513600
  },
  {
    "euro": 37.48,
    "timestamp": 1380517200
  },
  {
    "euro": 37.509998,
    "timestamp": 1380520800
  },
  {
    "euro": 37.470001,
    "timestamp": 1380524400
  },
  {
    "euro": 37.43,
    "timestamp": 1380528000
  },
  {
    "euro": 37.279999,
    "timestamp": 1380531600
  },
  {
    "euro": 37.27,
    "timestamp": 1380535200
  },
  {
    "euro": 37.349998,
    "timestamp": 1380538800
  },
  {
    "euro": 37.23,
    "timestamp": 1380542400
  },
  {
    "euro": 37.220001,
    "timestamp": 1380546000
  },
  {
    "euro": 37.209999,
    "timestamp": 1380549600
  },
  {
    "euro": 37.200001,
    "timestamp": 1380553200
  },
  {
    "euro": 37.25,
    "timestamp": 1380556800
  },
  {
    "euro": 37.279999,
    "timestamp": 1380560400
  },
  {
    "euro": 37.32,
    "timestamp": 1380564000
  },
  {
    "euro": 37.25,
    "timestamp": 1380567600
  },
  {
    "euro": 37.599998,
    "timestamp": 1380571200
  },
  {
    "euro": 37.619999,
    "timestamp": 1380574800
  },
  {
    "euro": 37.400002,
    "timestamp": 1380578400
  },
  {
    "euro": 37.34,
    "timestamp": 1380582000
  }
]
