[
  {
    "euro": 89.589996,
    "timestamp": 1687478400
  },
  {
    "euro": 89.089996,
    "timestamp": 1687482000
  },
  {
    "euro": 88.75,
    "timestamp": 1687485600
  },
  {
    "euro": 92.290001,
    "timestamp": 1687489200
  },
  {
    "euro": 112.32,
    "timestamp": 1687492800
  },
  {
    "euro": 125.839996,
    "timestamp": 1687496400
  },
  {
    "euro": 127.720001,
    "timestamp": 1687500000
  },
  {
    "euro": 118.730003,
    "timestamp": 1687503600
  },
  {
    "euro": 103.720001,
    "timestamp": 1687507200
  },
  {
    "euro": 95.75,
    "timestamp": 1687510800
  },
  {
    "euro": 90.769997,
    "timestamp": 1687514400
  },
  {
    "euro": 84.779999,
    "timestamp": 1687518000
  },
  {
    "euro": 78.059998,
    "timestamp": 1687521600
  },
  {
    "euro": 77.400002,
    "timestamp": 1687525200
  },
  {
    "euro": 77.400002,
    "timestamp": 1687528800
  },
  {
    "euro": 90.089996,
    "timestamp": 1687532400
  },
  {
    "euro": 104.910004,
    "timestamp": 1687536000
  },
  {
    "euro": 106.720001,
    "timestamp": 1687539600
  },
  {
    "euro": 133.809998,
    "timestamp": 1687543200
  },
  {
    "euro": 131.75,
    "timestamp": 1687546800
  },
  {
    "euro": 127.540001,
    "timestamp": 1687550400
  },
  {
    "euro": 119.389999,
    "timestamp": 1687554000
  }
]
