[
  {
    "euro": 82.019997,
    "timestamp": 1729641600
  },
  {
    "euro": 83.209999,
    "timestamp": 1729645200
  },
  {
    "euro": 85.800003,
    "timestamp": 1729648800
  },
  {
    "euro": 93.599998,
    "timestamp": 1729652400
  },
  {
    "euro": 108.190002,
    "timestamp": 1729656000
  },
  {
    "euro": 172.789993,
    "timestamp": 1729659600
  },
  {
    "euro": 183.130005,
    "timestamp": 1729663200
  },
  {
    "euro": 128.419998,
    "timestamp": 1729666800
  },
  {
    "euro": 104.099998,
    "timestamp": 1729670400
  },
  {
    "euro": 93.860001,
    "timestamp": 1729674000
  },
  {
    "euro": 85.620003,
    "timestamp": 1729677600
  },
  {
    "euro": 80.989998,
    "timestamp": 1729681200
  },
  {
    "euro": 78.970001,
    "timestamp": 1729684800
  },
  {
    "euro": 88.620003,
    "timestamp": 1729688400
  },
  {
    "euro": 101.900002,
    "timestamp": 1729692000
  },
  {
    "euro": 147.149994,
    "timestamp": 1729695600
  },
  {
    "euro": 218.179993,
    "timestamp": 1729699200
  },
  {
    "euro": 177.600006,
    "timestamp": 1729702800
  },
  {
    "euro": 111.709999,
    "timestamp": 1729706400
  },
  {
    "euro": 101.510002,
    "timestamp": 1729710000
  },
  {
    "euro": 103.330002,
    "timestamp": 1729713600
  },
  {
    "euro": 93.160004,
    "timestamp": 1729717200
  }
]
