[
  {
    "co2": 92,
    "timestamp": 1559260800
  },
  {
    "co2": 93,
    "timestamp": 1559261100
  },
  {
    "co2": 93,
    "timestamp": 1559261400
  },
  {
    "co2": 94,
    "timestamp": 1559261700
  },
  {
    "co2": 94,
    "timestamp": 1559262000
  },
  {
    "co2": 94,
    "timestamp": 1559262300
  },
  {
    "co2": 96,
    "timestamp": 1559262600
  },
  {
    "co2": 97,
    "timestamp": 1559262900
  },
  {
    "co2": 98,
    "timestamp": 1559263200
  },
  {
    "co2": 97,
    "timestamp": 1559263500
  },
  {
    "co2": 98,
    "timestamp": 1559263800
  },
  {
    "co2": 100,
    "timestamp": 1559264100
  },
  {
    "co2": 99,
    "timestamp": 1559264400
  },
  {
    "co2": 99,
    "timestamp": 1559264700
  },
  {
    "co2": 100,
    "timestamp": 1559265000
  },
  {
    "co2": 99,
    "timestamp": 1559265300
  },
  {
    "co2": 99,
    "timestamp": 1559265600
  },
  {
    "co2": 97,
    "timestamp": 1559265900
  },
  {
    "co2": 98,
    "timestamp": 1559266200
  },
  {
    "co2": 100,
    "timestamp": 1559266500
  },
  {
    "co2": 101,
    "timestamp": 1559266800
  },
  {
    "co2": 102,
    "timestamp": 1559267100
  },
  {
    "co2": 100,
    "timestamp": 1559267400
  },
  {
    "co2": 100,
    "timestamp": 1559267700
  },
  {
    "co2": 99,
    "timestamp": 1559268000
  },
  {
    "co2": 97,
    "timestamp": 1559268300
  },
  {
    "co2": 96,
    "timestamp": 1559268600
  },
  {
    "co2": 95,
    "timestamp": 1559268900
  },
  {
    "co2": 92,
    "timestamp": 1559269200
  },
  {
    "co2": 91,
    "timestamp": 1559269500
  },
  {
    "co2": 89,
    "timestamp": 1559269800
  },
  {
    "co2": 89,
    "timestamp": 1559270100
  },
  {
    "co2": 90,
    "timestamp": 1559270400
  },
  {
    "co2": 93,
    "timestamp": 1559270700
  },
  {
    "co2": 90,
    "timestamp": 1559271000
  },
  {
    "co2": 90,
    "timestamp": 1559271300
  },
  {
    "co2": 91,
    "timestamp": 1559271600
  },
  {
    "co2": 91,
    "timestamp": 1559271900
  },
  {
    "co2": 91,
    "timestamp": 1559272200
  },
  {
    "co2": 89,
    "timestamp": 1559272500
  },
  {
    "co2": 88,
    "timestamp": 1559272800
  },
  {
    "co2": 88,
    "timestamp": 1559273100
  },
  {
    "co2": 87,
    "timestamp": 1559273400
  },
  {
    "co2": 87,
    "timestamp": 1559273700
  },
  {
    "co2": 88,
    "timestamp": 1559274000
  },
  {
    "co2": 89,
    "timestamp": 1559274300
  },
  {
    "co2": 88,
    "timestamp": 1559274600
  },
  {
    "co2": 88,
    "timestamp": 1559274900
  },
  {
    "co2": 91,
    "timestamp": 1559275200
  },
  {
    "co2": 91,
    "timestamp": 1559275500
  },
  {
    "co2": 93,
    "timestamp": 1559275800
  },
  {
    "co2": 88,
    "timestamp": 1559276100
  },
  {
    "co2": 87,
    "timestamp": 1559276400
  },
  {
    "co2": 87,
    "timestamp": 1559276700
  },
  {
    "co2": 89,
    "timestamp": 1559277000
  },
  {
    "co2": 89,
    "timestamp": 1559277300
  },
  {
    "co2": 89,
    "timestamp": 1559277600
  },
  {
    "co2": 89,
    "timestamp": 1559277900
  },
  {
    "co2": 89,
    "timestamp": 1559278200
  },
  {
    "co2": 91,
    "timestamp": 1559278500
  },
  {
    "co2": 97,
    "timestamp": 1559278800
  },
  {
    "co2": 98,
    "timestamp": 1559279100
  },
  {
    "co2": 98,
    "timestamp": 1559279400
  },
  {
    "co2": 100,
    "timestamp": 1559279700
  },
  {
    "co2": 101,
    "timestamp": 1559280000
  },
  {
    "co2": 102,
    "timestamp": 1559280300
  },
  {
    "co2": 103,
    "timestamp": 1559280600
  },
  {
    "co2": 105,
    "timestamp": 1559280900
  },
  {
    "co2": 109,
    "timestamp": 1559281200
  },
  {
    "co2": 111,
    "timestamp": 1559281500
  },
  {
    "co2": 112,
    "timestamp": 1559281800
  },
  {
    "co2": 111,
    "timestamp": 1559282100
  },
  {
    "co2": 114,
    "timestamp": 1559282400
  },
  {
    "co2": 115,
    "timestamp": 1559282700
  },
  {
    "co2": 115,
    "timestamp": 1559283000
  },
  {
    "co2": 120,
    "timestamp": 1559283300
  },
  {
    "co2": 118,
    "timestamp": 1559283600
  },
  {
    "co2": 120,
    "timestamp": 1559283900
  },
  {
    "co2": 119,
    "timestamp": 1559284200
  },
  {
    "co2": 115,
    "timestamp": 1559284500
  },
  {
    "co2": 116,
    "timestamp": 1559284800
  },
  {
    "co2": 116,
    "timestamp": 1559285100
  },
  {
    "co2": 115,
    "timestamp": 1559285400
  },
  {
    "co2": 117,
    "timestamp": 1559285700
  },
  {
    "co2": 116,
    "timestamp": 1559286000
  },
  {
    "co2": 113,
    "timestamp": 1559286300
  },
  {
    "co2": 114,
    "timestamp": 1559286600
  },
  {
    "co2": 114,
    "timestamp": 1559286900
  },
  {
    "co2": 114,
    "timestamp": 1559287200
  },
  {
    "co2": 115,
    "timestamp": 1559287500
  },
  {
    "co2": 114,
    "timestamp": 1559287800
  },
  {
    "co2": 114,
    "timestamp": 1559288100
  },
  {
    "co2": 114,
    "timestamp": 1559288400
  },
  {
    "co2": 115,
    "timestamp": 1559288700
  },
  {
    "co2": 115,
    "timestamp": 1559289000
  },
  {
    "co2": 116,
    "timestamp": 1559289300
  },
  {
    "co2": 115,
    "timestamp": 1559289600
  },
  {
    "co2": 110,
    "timestamp": 1559289900
  },
  {
    "co2": 108,
    "timestamp": 1559290200
  },
  {
    "co2": 106,
    "timestamp": 1559290500
  },
  {
    "co2": 107,
    "timestamp": 1559290800
  },
  {
    "co2": 105,
    "timestamp": 1559291100
  },
  {
    "co2": 100,
    "timestamp": 1559291400
  },
  {
    "co2": 101,
    "timestamp": 1559291700
  },
  {
    "co2": 101,
    "timestamp": 1559292000
  },
  {
    "co2": 101,
    "timestamp": 1559292300
  },
  {
    "co2": 100,
    "timestamp": 1559292600
  },
  {
    "co2": 102,
    "timestamp": 1559292900
  },
  {
    "co2": 103,
    "timestamp": 1559293200
  },
  {
    "co2": 99,
    "timestamp": 1559293500
  },
  {
    "co2": 101,
    "timestamp": 1559293800
  },
  {
    "co2": 100,
    "timestamp": 1559294100
  },
  {
    "co2": 99,
    "timestamp": 1559294400
  },
  {
    "co2": 99,
    "timestamp": 1559294700
  },
  {
    "co2": 99,
    "timestamp": 1559295000
  },
  {
    "co2": 99,
    "timestamp": 1559295300
  },
  {
    "co2": 98,
    "timestamp": 1559295600
  },
  {
    "co2": 98,
    "timestamp": 1559295900
  },
  {
    "co2": 98,
    "timestamp": 1559296200
  },
  {
    "co2": 98,
    "timestamp": 1559296500
  },
  {
    "co2": 100,
    "timestamp": 1559296800
  },
  {
    "co2": 95,
    "timestamp": 1559297100
  },
  {
    "co2": 95,
    "timestamp": 1559297400
  },
  {
    "co2": 96,
    "timestamp": 1559297700
  },
  {
    "co2": 96,
    "timestamp": 1559298000
  },
  {
    "co2": 95,
    "timestamp": 1559298300
  },
  {
    "co2": 94,
    "timestamp": 1559298600
  },
  {
    "co2": 94,
    "timestamp": 1559298900
  },
  {
    "co2": 93,
    "timestamp": 1559299200
  },
  {
    "co2": 94,
    "timestamp": 1559299500
  },
  {
    "co2": 92,
    "timestamp": 1559299800
  },
  {
    "co2": 93,
    "timestamp": 1559300100
  },
  {
    "co2": 93,
    "timestamp": 1559300400
  },
  {
    "co2": 91,
    "timestamp": 1559300700
  },
  {
    "co2": 91,
    "timestamp": 1559301000
  },
  {
    "co2": 92,
    "timestamp": 1559301300
  },
  {
    "co2": 90,
    "timestamp": 1559301600
  },
  {
    "co2": 89,
    "timestamp": 1559301900
  },
  {
    "co2": 91,
    "timestamp": 1559302200
  },
  {
    "co2": 91,
    "timestamp": 1559302500
  },
  {
    "co2": 91,
    "timestamp": 1559302800
  },
  {
    "co2": 91,
    "timestamp": 1559303100
  },
  {
    "co2": 91,
    "timestamp": 1559303400
  },
  {
    "co2": 91,
    "timestamp": 1559303700
  },
  {
    "co2": 91,
    "timestamp": 1559304000
  },
  {
    "co2": 92,
    "timestamp": 1559304300
  },
  {
    "co2": 92,
    "timestamp": 1559304600
  },
  {
    "co2": 92,
    "timestamp": 1559304900
  },
  {
    "co2": 92,
    "timestamp": 1559305200
  },
  {
    "co2": 91,
    "timestamp": 1559305500
  },
  {
    "co2": 92,
    "timestamp": 1559305800
  },
  {
    "co2": 93,
    "timestamp": 1559306100
  },
  {
    "co2": 93,
    "timestamp": 1559306400
  },
  {
    "co2": 92,
    "timestamp": 1559306700
  },
  {
    "co2": 92,
    "timestamp": 1559307000
  },
  {
    "co2": 93,
    "timestamp": 1559307300
  },
  {
    "co2": 90,
    "timestamp": 1559307600
  },
  {
    "co2": 92,
    "timestamp": 1559307900
  },
  {
    "co2": 91,
    "timestamp": 1559308200
  },
  {
    "co2": 90,
    "timestamp": 1559308500
  },
  {
    "co2": 90,
    "timestamp": 1559308800
  },
  {
    "co2": 91,
    "timestamp": 1559309100
  },
  {
    "co2": 92,
    "timestamp": 1559309400
  },
  {
    "co2": 92,
    "timestamp": 1559309700
  },
  {
    "co2": 92,
    "timestamp": 1559310000
  },
  {
    "co2": 93,
    "timestamp": 1559310300
  },
  {
    "co2": 92,
    "timestamp": 1559310600
  },
  {
    "co2": 92,
    "timestamp": 1559310900
  },
  {
    "co2": 93,
    "timestamp": 1559311200
  },
  {
    "co2": 95,
    "timestamp": 1559311500
  },
  {
    "co2": 94,
    "timestamp": 1559311800
  },
  {
    "co2": 90,
    "timestamp": 1559312100
  },
  {
    "co2": 87,
    "timestamp": 1559312400
  },
  {
    "co2": 87,
    "timestamp": 1559312700
  },
  {
    "co2": 88,
    "timestamp": 1559313000
  },
  {
    "co2": 88,
    "timestamp": 1559313300
  },
  {
    "co2": 88,
    "timestamp": 1559313600
  },
  {
    "co2": 89,
    "timestamp": 1559313900
  },
  {
    "co2": 89,
    "timestamp": 1559314200
  },
  {
    "co2": 91,
    "timestamp": 1559314500
  },
  {
    "co2": 92,
    "timestamp": 1559314800
  },
  {
    "co2": 95,
    "timestamp": 1559315100
  },
  {
    "co2": 96,
    "timestamp": 1559315400
  },
  {
    "co2": 97,
    "timestamp": 1559315700
  },
  {
    "co2": 98,
    "timestamp": 1559316000
  },
  {
    "co2": 98,
    "timestamp": 1559316300
  },
  {
    "co2": 99,
    "timestamp": 1559316600
  },
  {
    "co2": 99,
    "timestamp": 1559316900
  },
  {
    "co2": 101,
    "timestamp": 1559317200
  },
  {
    "co2": 103,
    "timestamp": 1559317500
  },
  {
    "co2": 104,
    "timestamp": 1559317800
  },
  {
    "co2": 108,
    "timestamp": 1559318100
  },
  {
    "co2": 113,
    "timestamp": 1559318400
  },
  {
    "co2": 120,
    "timestamp": 1559318700
  },
  {
    "co2": 122,
    "timestamp": 1559319000
  },
  {
    "co2": 122,
    "timestamp": 1559319300
  },
  {
    "co2": 125,
    "timestamp": 1559319600
  },
  {
    "co2": 126,
    "timestamp": 1559319900
  },
  {
    "co2": 128,
    "timestamp": 1559320200
  },
  {
    "co2": 130,
    "timestamp": 1559320500
  },
  {
    "co2": 135,
    "timestamp": 1559320800
  },
  {
    "co2": 134,
    "timestamp": 1559321100
  },
  {
    "co2": 136,
    "timestamp": 1559321400
  },
  {
    "co2": 140,
    "timestamp": 1559321700
  },
  {
    "co2": 149,
    "timestamp": 1559322000
  },
  {
    "co2": 155,
    "timestamp": 1559322300
  },
  {
    "co2": 154,
    "timestamp": 1559322600
  },
  {
    "co2": 152,
    "timestamp": 1559322900
  },
  {
    "co2": 153,
    "timestamp": 1559323200
  },
  {
    "co2": 155,
    "timestamp": 1559323500
  },
  {
    "co2": 157,
    "timestamp": 1559323800
  },
  {
    "co2": 159,
    "timestamp": 1559324100
  },
  {
    "co2": 162,
    "timestamp": 1559324400
  },
  {
    "co2": 162,
    "timestamp": 1559324700
  },
  {
    "co2": 163,
    "timestamp": 1559325000
  },
  {
    "co2": 161,
    "timestamp": 1559325300
  },
  {
    "co2": 159,
    "timestamp": 1559325600
  },
  {
    "co2": 160,
    "timestamp": 1559325900
  },
  {
    "co2": 157,
    "timestamp": 1559326200
  },
  {
    "co2": 156,
    "timestamp": 1559326500
  },
  {
    "co2": 155,
    "timestamp": 1559326800
  },
  {
    "co2": 157,
    "timestamp": 1559327100
  },
  {
    "co2": 157,
    "timestamp": 1559327400
  },
  {
    "co2": 158,
    "timestamp": 1559327700
  },
  {
    "co2": 160,
    "timestamp": 1559328000
  },
  {
    "co2": 165,
    "timestamp": 1559328300
  },
  {
    "co2": 169,
    "timestamp": 1559328600
  },
  {
    "co2": 175,
    "timestamp": 1559328900
  },
  {
    "co2": 176,
    "timestamp": 1559329200
  },
  {
    "co2": 181,
    "timestamp": 1559329500
  },
  {
    "co2": 184,
    "timestamp": 1559329800
  },
  {
    "co2": 187,
    "timestamp": 1559330100
  },
  {
    "co2": 183,
    "timestamp": 1559330400
  },
  {
    "co2": 183,
    "timestamp": 1559330700
  },
  {
    "co2": 182,
    "timestamp": 1559331000
  },
  {
    "co2": 179,
    "timestamp": 1559331300
  },
  {
    "co2": 175,
    "timestamp": 1559331600
  },
  {
    "co2": 174,
    "timestamp": 1559331900
  },
  {
    "co2": 171,
    "timestamp": 1559332200
  },
  {
    "co2": 170,
    "timestamp": 1559332500
  },
  {
    "co2": 167,
    "timestamp": 1559332800
  },
  {
    "co2": 161,
    "timestamp": 1559333100
  },
  {
    "co2": 158,
    "timestamp": 1559333400
  },
  {
    "co2": 154,
    "timestamp": 1559333700
  },
  {
    "co2": 150,
    "timestamp": 1559334000
  },
  {
    "co2": 149,
    "timestamp": 1559334300
  },
  {
    "co2": 152,
    "timestamp": 1559334600
  },
  {
    "co2": 150,
    "timestamp": 1559334900
  },
  {
    "co2": 154,
    "timestamp": 1559335200
  },
  {
    "co2": 148,
    "timestamp": 1559335500
  },
  {
    "co2": 145,
    "timestamp": 1559335800
  },
  {
    "co2": 140,
    "timestamp": 1559336100
  },
  {
    "co2": 143,
    "timestamp": 1559336400
  },
  {
    "co2": 134,
    "timestamp": 1559336700
  },
  {
    "co2": 130,
    "timestamp": 1559337000
  },
  {
    "co2": 129,
    "timestamp": 1559337300
  },
  {
    "co2": 129,
    "timestamp": 1559337600
  },
  {
    "co2": 128,
    "timestamp": 1559337900
  },
  {
    "co2": 127,
    "timestamp": 1559338200
  },
  {
    "co2": 126,
    "timestamp": 1559338500
  },
  {
    "co2": 126,
    "timestamp": 1559338800
  },
  {
    "co2": 126,
    "timestamp": 1559339100
  },
  {
    "co2": 125,
    "timestamp": 1559339400
  },
  {
    "co2": 125,
    "timestamp": 1559339700
  },
  {
    "co2": 110,
    "timestamp": 1559340000
  },
  {
    "co2": 105,
    "timestamp": 1559340300
  },
  {
    "co2": 101,
    "timestamp": 1559340600
  },
  {
    "co2": 97,
    "timestamp": 1559340900
  },
  {
    "co2": 89,
    "timestamp": 1559341200
  },
  {
    "co2": 87,
    "timestamp": 1559341500
  },
  {
    "co2": 88,
    "timestamp": 1559341800
  },
  {
    "co2": 85,
    "timestamp": 1559342100
  },
  {
    "co2": 82,
    "timestamp": 1559342400
  },
  {
    "co2": 79,
    "timestamp": 1559342700
  },
  {
    "co2": 78,
    "timestamp": 1559343000
  },
  {
    "co2": 77,
    "timestamp": 1559343300
  },
  {
    "co2": 77,
    "timestamp": 1559343600
  },
  {
    "co2": 76,
    "timestamp": 1559343900
  },
  {
    "co2": 75,
    "timestamp": 1559344200
  },
  {
    "co2": 76,
    "timestamp": 1559344500
  },
  {
    "co2": 74,
    "timestamp": 1559344800
  },
  {
    "co2": 74,
    "timestamp": 1559345100
  },
  {
    "co2": 73,
    "timestamp": 1559345400
  },
  {
    "co2": 71,
    "timestamp": 1559345700
  },
  {
    "co2": 71,
    "timestamp": 1559346000
  },
  {
    "co2": 70,
    "timestamp": 1559346300
  },
  {
    "co2": 68,
    "timestamp": 1559346600
  },
  {
    "co2": 65,
    "timestamp": 1559346900
  }
]
