[
  {
    "euro": 38.990002,
    "timestamp": 1216425600
  },
  {
    "euro": 38.779999,
    "timestamp": 1216429200
  },
  {
    "euro": 36.439999,
    "timestamp": 1216432800
  },
  {
    "euro": 31.02,
    "timestamp": 1216436400
  },
  {
    "euro": 34.599998,
    "timestamp": 1216440000
  },
  {
    "euro": 37.970001,
    "timestamp": 1216443600
  },
  {
    "euro": 38.130001,
    "timestamp": 1216447200
  },
  {
    "euro": 38.5,
    "timestamp": 1216450800
  },
  {
    "euro": 38.790001,
    "timestamp": 1216454400
  },
  {
    "euro": 38.939999,
    "timestamp": 1216458000
  },
  {
    "euro": 38.790001,
    "timestamp": 1216461600
  },
  {
    "euro": 38.68,
    "timestamp": 1216465200
  },
  {
    "euro": 38.610001,
    "timestamp": 1216468800
  },
  {
    "euro": 38.580002,
    "timestamp": 1216472400
  },
  {
    "euro": 38.860001,
    "timestamp": 1216476000
  },
  {
    "euro": 38.91,
    "timestamp": 1216479600
  },
  {
    "euro": 38.919998,
    "timestamp": 1216483200
  },
  {
    "euro": 38.57,
    "timestamp": 1216486800
  },
  {
    "euro": 38.57,
    "timestamp": 1216490400
  },
  {
    "euro": 38.52,
    "timestamp": 1216494000
  },
  {
    "euro": 38.689999,
    "timestamp": 1216497600
  },
  {
    "euro": 38.720001,
    "timestamp": 1216501200
  },
  {
    "euro": 38.970001,
    "timestamp": 1216504800
  },
  {
    "euro": 35.759998,
    "timestamp": 1216508400
  }
]
