[
  {
    "euro": 22.17,
    "timestamp": 1341014400
  },
  {
    "euro": 21.799999,
    "timestamp": 1341018000
  },
  {
    "euro": 21.530001,
    "timestamp": 1341021600
  },
  {
    "euro": 21.67,
    "timestamp": 1341025200
  },
  {
    "euro": 29.110001,
    "timestamp": 1341028800
  },
  {
    "euro": 35.029999,
    "timestamp": 1341032400
  },
  {
    "euro": 41.32,
    "timestamp": 1341036000
  },
  {
    "euro": 43.75,
    "timestamp": 1341039600
  },
  {
    "euro": 42.099998,
    "timestamp": 1341043200
  },
  {
    "euro": 42.900002,
    "timestamp": 1341046800
  },
  {
    "euro": 39.540001,
    "timestamp": 1341050400
  },
  {
    "euro": 32.080002,
    "timestamp": 1341054000
  },
  {
    "euro": 27.93,
    "timestamp": 1341057600
  },
  {
    "euro": 31.35,
    "timestamp": 1341061200
  },
  {
    "euro": 34.700001,
    "timestamp": 1341064800
  },
  {
    "euro": 39.349998,
    "timestamp": 1341068400
  },
  {
    "euro": 45.540001,
    "timestamp": 1341072000
  },
  {
    "euro": 45,
    "timestamp": 1341075600
  },
  {
    "euro": 42.93,
    "timestamp": 1341079200
  },
  {
    "euro": 41.939999,
    "timestamp": 1341082800
  },
  {
    "euro": 45.290001,
    "timestamp": 1341086400
  },
  {
    "euro": 38.66,
    "timestamp": 1341090000
  },
  {
    "euro": 34.07,
    "timestamp": 1341093600
  },
  {
    "euro": 25.309999,
    "timestamp": 1341097200
  }
]
