[
  {
    "euro": 20.709999,
    "timestamp": 1283904000
  },
  {
    "euro": 9.83,
    "timestamp": 1283907600
  },
  {
    "euro": 13.01,
    "timestamp": 1283911200
  },
  {
    "euro": 25.01,
    "timestamp": 1283914800
  },
  {
    "euro": 47.59,
    "timestamp": 1283918400
  },
  {
    "euro": 51.48,
    "timestamp": 1283922000
  },
  {
    "euro": 53.740002,
    "timestamp": 1283925600
  },
  {
    "euro": 49.310001,
    "timestamp": 1283929200
  },
  {
    "euro": 49.610001,
    "timestamp": 1283932800
  },
  {
    "euro": 51.720001,
    "timestamp": 1283936400
  },
  {
    "euro": 49.810001,
    "timestamp": 1283940000
  },
  {
    "euro": 49.369999,
    "timestamp": 1283943600
  },
  {
    "euro": 48.93,
    "timestamp": 1283947200
  },
  {
    "euro": 48.310001,
    "timestamp": 1283950800
  },
  {
    "euro": 47.560001,
    "timestamp": 1283954400
  },
  {
    "euro": 47.119999,
    "timestamp": 1283958000
  },
  {
    "euro": 49.41,
    "timestamp": 1283961600
  },
  {
    "euro": 49.509998,
    "timestamp": 1283965200
  },
  {
    "euro": 55.810001,
    "timestamp": 1283968800
  },
  {
    "euro": 49.84,
    "timestamp": 1283972400
  },
  {
    "euro": 47.060001,
    "timestamp": 1283976000
  },
  {
    "euro": 41.900002,
    "timestamp": 1283979600
  },
  {
    "euro": 28.76,
    "timestamp": 1283983200
  },
  {
    "euro": 24.93,
    "timestamp": 1283986800
  }
]
