[
  {
    "co2": 217,
    "timestamp": 1504224000
  },
  {
    "co2": 221,
    "timestamp": 1504224300
  },
  {
    "co2": 236,
    "timestamp": 1504224600
  },
  {
    "co2": 237,
    "timestamp": 1504224900
  },
  {
    "co2": 236,
    "timestamp": 1504225200
  },
  {
    "co2": 229,
    "timestamp": 1504225500
  },
  {
    "co2": 229,
    "timestamp": 1504225800
  },
  {
    "co2": 229,
    "timestamp": 1504226100
  },
  {
    "co2": 229,
    "timestamp": 1504226400
  },
  {
    "co2": 229,
    "timestamp": 1504226700
  },
  {
    "co2": 236,
    "timestamp": 1504227000
  },
  {
    "co2": 236,
    "timestamp": 1504227300
  },
  {
    "co2": 236,
    "timestamp": 1504227600
  },
  {
    "co2": 236,
    "timestamp": 1504227900
  },
  {
    "co2": 236,
    "timestamp": 1504228200
  },
  {
    "co2": 237,
    "timestamp": 1504228500
  },
  {
    "co2": 237,
    "timestamp": 1504228800
  },
  {
    "co2": 237,
    "timestamp": 1504229100
  },
  {
    "co2": 236,
    "timestamp": 1504229400
  },
  {
    "co2": 243,
    "timestamp": 1504229700
  },
  {
    "co2": 243,
    "timestamp": 1504230000
  },
  {
    "co2": 243,
    "timestamp": 1504230300
  },
  {
    "co2": 250,
    "timestamp": 1504230600
  },
  {
    "co2": 250,
    "timestamp": 1504230900
  },
  {
    "co2": 251,
    "timestamp": 1504231200
  },
  {
    "co2": 252,
    "timestamp": 1504231500
  },
  {
    "co2": 262,
    "timestamp": 1504231800
  },
  {
    "co2": 262,
    "timestamp": 1504232100
  },
  {
    "co2": 262,
    "timestamp": 1504232400
  },
  {
    "co2": 300,
    "timestamp": 1504232700
  },
  {
    "co2": 300,
    "timestamp": 1504233000
  },
  {
    "co2": 301,
    "timestamp": 1504233300
  },
  {
    "co2": 307,
    "timestamp": 1504233600
  },
  {
    "co2": 307,
    "timestamp": 1504233900
  },
  {
    "co2": 307,
    "timestamp": 1504234200
  },
  {
    "co2": 307,
    "timestamp": 1504234500
  },
  {
    "co2": 275,
    "timestamp": 1504234800
  },
  {
    "co2": 251,
    "timestamp": 1504235100
  },
  {
    "co2": 240,
    "timestamp": 1504235400
  },
  {
    "co2": 225,
    "timestamp": 1504235700
  },
  {
    "co2": 225,
    "timestamp": 1504236000
  },
  {
    "co2": 224,
    "timestamp": 1504236300
  },
  {
    "co2": 239,
    "timestamp": 1504236600
  },
  {
    "co2": 247,
    "timestamp": 1504236900
  },
  {
    "co2": 254,
    "timestamp": 1504237200
  },
  {
    "co2": 254,
    "timestamp": 1504237500
  },
  {
    "co2": 256,
    "timestamp": 1504237800
  },
  {
    "co2": 245,
    "timestamp": 1504238100
  },
  {
    "co2": 239,
    "timestamp": 1504238400
  },
  {
    "co2": 234,
    "timestamp": 1504238700
  },
  {
    "co2": 235,
    "timestamp": 1504239000
  },
  {
    "co2": 243,
    "timestamp": 1504239300
  },
  {
    "co2": 246,
    "timestamp": 1504239600
  },
  {
    "co2": 253,
    "timestamp": 1504239900
  },
  {
    "co2": 260,
    "timestamp": 1504240200
  },
  {
    "co2": 260,
    "timestamp": 1504240500
  },
  {
    "co2": 261,
    "timestamp": 1504240800
  },
  {
    "co2": 268,
    "timestamp": 1504241100
  },
  {
    "co2": 271,
    "timestamp": 1504241400
  },
  {
    "co2": 284,
    "timestamp": 1504241700
  },
  {
    "co2": 291,
    "timestamp": 1504242000
  },
  {
    "co2": 325,
    "timestamp": 1504242300
  },
  {
    "co2": 340,
    "timestamp": 1504242600
  },
  {
    "co2": 341,
    "timestamp": 1504242900
  },
  {
    "co2": 349,
    "timestamp": 1504243200
  },
  {
    "co2": 357,
    "timestamp": 1504243500
  },
  {
    "co2": 358,
    "timestamp": 1504243800
  },
  {
    "co2": 361,
    "timestamp": 1504244100
  },
  {
    "co2": 357,
    "timestamp": 1504244400
  },
  {
    "co2": 367,
    "timestamp": 1504244700
  },
  {
    "co2": 369,
    "timestamp": 1504245000
  },
  {
    "co2": 364,
    "timestamp": 1504245300
  },
  {
    "co2": 380,
    "timestamp": 1504245600
  },
  {
    "co2": 397,
    "timestamp": 1504245900
  },
  {
    "co2": 398,
    "timestamp": 1504246200
  },
  {
    "co2": 402,
    "timestamp": 1504246500
  },
  {
    "co2": 402,
    "timestamp": 1504246800
  },
  {
    "co2": 395,
    "timestamp": 1504247100
  },
  {
    "co2": 395,
    "timestamp": 1504247400
  },
  {
    "co2": 393,
    "timestamp": 1504247700
  },
  {
    "co2": 391,
    "timestamp": 1504248000
  },
  {
    "co2": 392,
    "timestamp": 1504248300
  },
  {
    "co2": 393,
    "timestamp": 1504248600
  },
  {
    "co2": 390,
    "timestamp": 1504248900
  },
  {
    "co2": 398,
    "timestamp": 1504249200
  },
  {
    "co2": 392,
    "timestamp": 1504249500
  },
  {
    "co2": 393,
    "timestamp": 1504249800
  },
  {
    "co2": 392,
    "timestamp": 1504250100
  },
  {
    "co2": 392,
    "timestamp": 1504250400
  },
  {
    "co2": 392,
    "timestamp": 1504250700
  },
  {
    "co2": 392,
    "timestamp": 1504251000
  },
  {
    "co2": 393,
    "timestamp": 1504251300
  },
  {
    "co2": 400,
    "timestamp": 1504251600
  },
  {
    "co2": 399,
    "timestamp": 1504251900
  },
  {
    "co2": 400,
    "timestamp": 1504252200
  },
  {
    "co2": 387,
    "timestamp": 1504252500
  },
  {
    "co2": 384,
    "timestamp": 1504252800
  },
  {
    "co2": 391,
    "timestamp": 1504253100
  },
  {
    "co2": 391,
    "timestamp": 1504253400
  },
  {
    "co2": 390,
    "timestamp": 1504253700
  },
  {
    "co2": 397,
    "timestamp": 1504254000
  },
  {
    "co2": 397,
    "timestamp": 1504254300
  },
  {
    "co2": 384,
    "timestamp": 1504254600
  },
  {
    "co2": 373,
    "timestamp": 1504254900
  },
  {
    "co2": 372,
    "timestamp": 1504255200
  },
  {
    "co2": 366,
    "timestamp": 1504255500
  },
  {
    "co2": 366,
    "timestamp": 1504255800
  },
  {
    "co2": 366,
    "timestamp": 1504256100
  },
  {
    "co2": 356,
    "timestamp": 1504256400
  },
  {
    "co2": 346,
    "timestamp": 1504256700
  },
  {
    "co2": 348,
    "timestamp": 1504257000
  },
  {
    "co2": 351,
    "timestamp": 1504257300
  },
  {
    "co2": 351,
    "timestamp": 1504257600
  },
  {
    "co2": 351,
    "timestamp": 1504257900
  },
  {
    "co2": 351,
    "timestamp": 1504258200
  },
  {
    "co2": 351,
    "timestamp": 1504258500
  },
  {
    "co2": 358,
    "timestamp": 1504258800
  },
  {
    "co2": 358,
    "timestamp": 1504259100
  },
  {
    "co2": 356,
    "timestamp": 1504259400
  },
  {
    "co2": 365,
    "timestamp": 1504259700
  },
  {
    "co2": 371,
    "timestamp": 1504260000
  },
  {
    "co2": 370,
    "timestamp": 1504260300
  },
  {
    "co2": 369,
    "timestamp": 1504260600
  },
  {
    "co2": 375,
    "timestamp": 1504260900
  },
  {
    "co2": 375,
    "timestamp": 1504261200
  },
  {
    "co2": 375,
    "timestamp": 1504261500
  },
  {
    "co2": 368,
    "timestamp": 1504261800
  },
  {
    "co2": 368,
    "timestamp": 1504262100
  },
  {
    "co2": 368,
    "timestamp": 1504262400
  },
  {
    "co2": 375,
    "timestamp": 1504262700
  },
  {
    "co2": 367,
    "timestamp": 1504263000
  },
  {
    "co2": 353,
    "timestamp": 1504263300
  },
  {
    "co2": 345,
    "timestamp": 1504263600
  },
  {
    "co2": 342,
    "timestamp": 1504263900
  },
  {
    "co2": 343,
    "timestamp": 1504264200
  },
  {
    "co2": 343,
    "timestamp": 1504264500
  },
  {
    "co2": 342,
    "timestamp": 1504264800
  },
  {
    "co2": 342,
    "timestamp": 1504265100
  },
  {
    "co2": 335,
    "timestamp": 1504265400
  },
  {
    "co2": 335,
    "timestamp": 1504265700
  },
  {
    "co2": 335,
    "timestamp": 1504266000
  },
  {
    "co2": 335,
    "timestamp": 1504266300
  },
  {
    "co2": 336,
    "timestamp": 1504266600
  },
  {
    "co2": 336,
    "timestamp": 1504266900
  },
  {
    "co2": 337,
    "timestamp": 1504267200
  },
  {
    "co2": 336,
    "timestamp": 1504267500
  },
  {
    "co2": 336,
    "timestamp": 1504267800
  },
  {
    "co2": 336,
    "timestamp": 1504268100
  },
  {
    "co2": 336,
    "timestamp": 1504268400
  },
  {
    "co2": 335,
    "timestamp": 1504268700
  },
  {
    "co2": 335,
    "timestamp": 1504269000
  },
  {
    "co2": 335,
    "timestamp": 1504269300
  },
  {
    "co2": 335,
    "timestamp": 1504269600
  },
  {
    "co2": 335,
    "timestamp": 1504269900
  },
  {
    "co2": 334,
    "timestamp": 1504270200
  },
  {
    "co2": 333,
    "timestamp": 1504270500
  },
  {
    "co2": 341,
    "timestamp": 1504270800
  },
  {
    "co2": 355,
    "timestamp": 1504271100
  },
  {
    "co2": 361,
    "timestamp": 1504271400
  },
  {
    "co2": 361,
    "timestamp": 1504271700
  },
  {
    "co2": 361,
    "timestamp": 1504272000
  },
  {
    "co2": 361,
    "timestamp": 1504272300
  },
  {
    "co2": 349,
    "timestamp": 1504272600
  },
  {
    "co2": 341,
    "timestamp": 1504272900
  },
  {
    "co2": 341,
    "timestamp": 1504273200
  },
  {
    "co2": 341,
    "timestamp": 1504273500
  },
  {
    "co2": 334,
    "timestamp": 1504273800
  },
  {
    "co2": 335,
    "timestamp": 1504274100
  },
  {
    "co2": 361,
    "timestamp": 1504274400
  },
  {
    "co2": 389,
    "timestamp": 1504274700
  },
  {
    "co2": 389,
    "timestamp": 1504275000
  },
  {
    "co2": 383,
    "timestamp": 1504275300
  },
  {
    "co2": 390,
    "timestamp": 1504275600
  },
  {
    "co2": 390,
    "timestamp": 1504275900
  },
  {
    "co2": 390,
    "timestamp": 1504276200
  },
  {
    "co2": 397,
    "timestamp": 1504276500
  },
  {
    "co2": 397,
    "timestamp": 1504276800
  },
  {
    "co2": 396,
    "timestamp": 1504277100
  },
  {
    "co2": 397,
    "timestamp": 1504277400
  },
  {
    "co2": 381,
    "timestamp": 1504277700
  },
  {
    "co2": 354,
    "timestamp": 1504278000
  },
  {
    "co2": 328,
    "timestamp": 1504278300
  },
  {
    "co2": 321,
    "timestamp": 1504278600
  },
  {
    "co2": 321,
    "timestamp": 1504278900
  },
  {
    "co2": 321,
    "timestamp": 1504279200
  },
  {
    "co2": 321,
    "timestamp": 1504279500
  },
  {
    "co2": 329,
    "timestamp": 1504279800
  },
  {
    "co2": 329,
    "timestamp": 1504280100
  },
  {
    "co2": 337,
    "timestamp": 1504280400
  },
  {
    "co2": 337,
    "timestamp": 1504280700
  },
  {
    "co2": 328,
    "timestamp": 1504281000
  },
  {
    "co2": 328,
    "timestamp": 1504281300
  },
  {
    "co2": 337,
    "timestamp": 1504281600
  },
  {
    "co2": 335,
    "timestamp": 1504281900
  },
  {
    "co2": 335,
    "timestamp": 1504282200
  },
  {
    "co2": 341,
    "timestamp": 1504282500
  },
  {
    "co2": 341,
    "timestamp": 1504282800
  },
  {
    "co2": 341,
    "timestamp": 1504283100
  },
  {
    "co2": 341,
    "timestamp": 1504283400
  },
  {
    "co2": 341,
    "timestamp": 1504283700
  },
  {
    "co2": 349,
    "timestamp": 1504284000
  },
  {
    "co2": 356,
    "timestamp": 1504284300
  },
  {
    "co2": 357,
    "timestamp": 1504284600
  },
  {
    "co2": 356,
    "timestamp": 1504284900
  },
  {
    "co2": 349,
    "timestamp": 1504285200
  },
  {
    "co2": 340,
    "timestamp": 1504285500
  },
  {
    "co2": 327,
    "timestamp": 1504285800
  },
  {
    "co2": 334,
    "timestamp": 1504286100
  },
  {
    "co2": 333,
    "timestamp": 1504286400
  },
  {
    "co2": 334,
    "timestamp": 1504286700
  },
  {
    "co2": 334,
    "timestamp": 1504287000
  },
  {
    "co2": 334,
    "timestamp": 1504287300
  },
  {
    "co2": 334,
    "timestamp": 1504287600
  },
  {
    "co2": 334,
    "timestamp": 1504287900
  },
  {
    "co2": 334,
    "timestamp": 1504288200
  },
  {
    "co2": 334,
    "timestamp": 1504288500
  },
  {
    "co2": 334,
    "timestamp": 1504288800
  },
  {
    "co2": 329,
    "timestamp": 1504289100
  },
  {
    "co2": 329,
    "timestamp": 1504289400
  },
  {
    "co2": 327,
    "timestamp": 1504289700
  },
  {
    "co2": 327,
    "timestamp": 1504290000
  },
  {
    "co2": 327,
    "timestamp": 1504290300
  },
  {
    "co2": 327,
    "timestamp": 1504290600
  },
  {
    "co2": 327,
    "timestamp": 1504290900
  },
  {
    "co2": 326,
    "timestamp": 1504291200
  },
  {
    "co2": 326,
    "timestamp": 1504291500
  },
  {
    "co2": 320,
    "timestamp": 1504291800
  },
  {
    "co2": 320,
    "timestamp": 1504292100
  },
  {
    "co2": 320,
    "timestamp": 1504292400
  },
  {
    "co2": 307,
    "timestamp": 1504292700
  },
  {
    "co2": 300,
    "timestamp": 1504293000
  },
  {
    "co2": 295,
    "timestamp": 1504293300
  },
  {
    "co2": 296,
    "timestamp": 1504293600
  },
  {
    "co2": 296,
    "timestamp": 1504293900
  },
  {
    "co2": 296,
    "timestamp": 1504294200
  },
  {
    "co2": 297,
    "timestamp": 1504294500
  },
  {
    "co2": 297,
    "timestamp": 1504294800
  },
  {
    "co2": 297,
    "timestamp": 1504295100
  },
  {
    "co2": 289,
    "timestamp": 1504295400
  },
  {
    "co2": 288,
    "timestamp": 1504295700
  },
  {
    "co2": 286,
    "timestamp": 1504296000
  },
  {
    "co2": 287,
    "timestamp": 1504296300
  },
  {
    "co2": 285,
    "timestamp": 1504296600
  },
  {
    "co2": 285,
    "timestamp": 1504296900
  },
  {
    "co2": 285,
    "timestamp": 1504297200
  },
  {
    "co2": 285,
    "timestamp": 1504297500
  },
  {
    "co2": 285,
    "timestamp": 1504297800
  },
  {
    "co2": 285,
    "timestamp": 1504298100
  },
  {
    "co2": 285,
    "timestamp": 1504298400
  },
  {
    "co2": 285,
    "timestamp": 1504298700
  },
  {
    "co2": 285,
    "timestamp": 1504299000
  },
  {
    "co2": 285,
    "timestamp": 1504299300
  },
  {
    "co2": 257,
    "timestamp": 1504299600
  },
  {
    "co2": 244,
    "timestamp": 1504299900
  },
  {
    "co2": 244,
    "timestamp": 1504300200
  },
  {
    "co2": 244,
    "timestamp": 1504300500
  },
  {
    "co2": 244,
    "timestamp": 1504300800
  },
  {
    "co2": 244,
    "timestamp": 1504301100
  },
  {
    "co2": 251,
    "timestamp": 1504301400
  },
  {
    "co2": 251,
    "timestamp": 1504301700
  },
  {
    "co2": 237,
    "timestamp": 1504302000
  },
  {
    "co2": 224,
    "timestamp": 1504302300
  },
  {
    "co2": 211,
    "timestamp": 1504302600
  },
  {
    "co2": 214,
    "timestamp": 1504302900
  },
  {
    "co2": 226,
    "timestamp": 1504303200
  },
  {
    "co2": 247,
    "timestamp": 1504303500
  },
  {
    "co2": 247,
    "timestamp": 1504303800
  },
  {
    "co2": 243,
    "timestamp": 1504304100
  },
  {
    "co2": 214,
    "timestamp": 1504304400
  },
  {
    "co2": 202,
    "timestamp": 1504304700
  },
  {
    "co2": 196,
    "timestamp": 1504305000
  },
  {
    "co2": 190,
    "timestamp": 1504305300
  },
  {
    "co2": 184,
    "timestamp": 1504305600
  },
  {
    "co2": 172,
    "timestamp": 1504305900
  },
  {
    "co2": 178,
    "timestamp": 1504306200
  },
  {
    "co2": 188,
    "timestamp": 1504306500
  },
  {
    "co2": 186,
    "timestamp": 1504306800
  },
  {
    "co2": 193,
    "timestamp": 1504307100
  },
  {
    "co2": 202,
    "timestamp": 1504307400
  },
  {
    "co2": 208,
    "timestamp": 1504307700
  },
  {
    "co2": 208,
    "timestamp": 1504308000
  },
  {
    "co2": 208,
    "timestamp": 1504308300
  },
  {
    "co2": 208,
    "timestamp": 1504308600
  },
  {
    "co2": 208,
    "timestamp": 1504308900
  },
  {
    "co2": 208,
    "timestamp": 1504309200
  },
  {
    "co2": 208,
    "timestamp": 1504309500
  },
  {
    "co2": 217,
    "timestamp": 1504309800
  },
  {
    "co2": 234,
    "timestamp": 1504310100
  }
]
