[
  {
    "euro": 43.060001,
    "timestamp": 1194652800
  },
  {
    "euro": 42.900002,
    "timestamp": 1194656400
  },
  {
    "euro": 42.790001,
    "timestamp": 1194660000
  },
  {
    "euro": 42.849998,
    "timestamp": 1194663600
  },
  {
    "euro": 42.919998,
    "timestamp": 1194667200
  },
  {
    "euro": 43.209999,
    "timestamp": 1194670800
  },
  {
    "euro": 43.259998,
    "timestamp": 1194674400
  },
  {
    "euro": 43.330002,
    "timestamp": 1194678000
  },
  {
    "euro": 43.869999,
    "timestamp": 1194681600
  },
  {
    "euro": 44.150002,
    "timestamp": 1194685200
  },
  {
    "euro": 44.080002,
    "timestamp": 1194688800
  },
  {
    "euro": 43.650002,
    "timestamp": 1194692400
  },
  {
    "euro": 43.240002,
    "timestamp": 1194696000
  },
  {
    "euro": 43.130001,
    "timestamp": 1194699600
  },
  {
    "euro": 43.32,
    "timestamp": 1194703200
  },
  {
    "euro": 44.169998,
    "timestamp": 1194706800
  },
  {
    "euro": 46.009998,
    "timestamp": 1194710400
  },
  {
    "euro": 46.349998,
    "timestamp": 1194714000
  },
  {
    "euro": 44.98,
    "timestamp": 1194717600
  },
  {
    "euro": 43.669998,
    "timestamp": 1194721200
  },
  {
    "euro": 43.400002,
    "timestamp": 1194724800
  },
  {
    "euro": 43.209999,
    "timestamp": 1194728400
  },
  {
    "euro": 43.029999,
    "timestamp": 1194732000
  },
  {
    "euro": 43.509998,
    "timestamp": 1194735600
  }
]
